polodb.cpython-39-darwin.so
polodb-0.10.4.data/data/include/polodb.h
polodb-0.10.4.dist-info/METADATA
polodb-0.10.4.dist-info/WHEEL
polodb-0.10.4.dist-info/top_level.txt
polodb-0.10.4.dist-info/RECORD
