Metadata-Version: 2.1
Name: polodb
Version: 0.10.4
Summary: PoloDB for Python
Home-page: UNKNOWN
Author: Vincent Chan
Author-email: okcdz@diverse.space
License: MIT
Platform: UNKNOWN
